LibRadar/__init__.py
LibRadar/_settings.py
LibRadar/api_dictionary.py
LibRadar/app_extracting.py
LibRadar/app_preprocessing.py
LibRadar/db_dumping.py
LibRadar/dex_extracting.py
LibRadar/dex_parser.py
LibRadar/dex_tree.py
LibRadar/feature_extracting.py
LibRadar/job_dispatching.py
LibRadar/lib_tagging.py
LibRadar/lib_tagging_gui.py
LibRadar/libradar.py
libradar-2.0b7.dist-info/DESCRIPTION.rst
libradar-2.0b7.dist-info/METADATA
libradar-2.0b7.dist-info/metadata.json
libradar-2.0b7.dist-info/RECORD
libradar-2.0b7.dist-info/top_level.txt
libradar-2.0b7.dist-info/WHEEL
