Metadata-Version: 2.0
Name: libradar
Version: 2.0b7
Summary: A tool for Android library detection.
Home-page: https://github.com/pkumza/libradar
Author: Zachary Marv (马子昂)
Author-email: ma@zablog.me
License: Apache License, Version 2.0
Keywords: Android Third-party Library
Platform: UNKNOWN
Classifier: Development Status :: 4 - Beta
Classifier: Programming Language :: Python :: 2.7
Classifier: Programming Language :: Python :: 2 :: Only
Classifier: Operating System :: MacOS :: MacOS X
Classifier: Operating System :: POSIX :: Linux
Classifier: Topic :: Security
Classifier: Topic :: Utilities
Classifier: License :: OSI Approved :: Apache Software License
Requires: redis
